LICENSE
README.md
pyproject.toml
setup.py
bark_python/__init__.py
bark_python/client.py
bark_python/exceptions.py
bark_python.egg-info/PKG-INFO
bark_python.egg-info/SOURCES.txt
bark_python.egg-info/dependency_links.txt
bark_python.egg-info/not-zip-safe
bark_python.egg-info/requires.txt
bark_python.egg-info/top_level.txt