Metadata-Version: 2.4
Name: bark_python
Version: 0.1.0
Summary: Bark encrypted push client
Home-page: https://github.com/horennel/bark-python
Author: horennel
Author-email: horennel <nelsonhoren@gmail.com>
License: MIT
Project-URL: Homepage, https://github.com/horennel/bark-python
Classifier: Programming Language :: Python :: 3
Classifier: Operating System :: OS Independent
Requires-Python: >=3.6
License-File: LICENSE
Requires-Dist: requests~=2.32.4
Requires-Dist: pycryptodome~=3.23.0
Dynamic: author
Dynamic: home-page
Dynamic: license-file
Dynamic: requires-python
